pelican/plugins/sitemap/__init__.py
pelican/plugins/sitemap/sitemap.py
pelican/plugins/sitemap/test_sitemap.py
pelican_sitemap-1.2.2.dist-info/METADATA
pelican_sitemap-1.2.2.dist-info/WHEEL
pelican_sitemap-1.2.2.dist-info/entry_points.txt
pelican_sitemap-1.2.2.dist-info/RECORD
